serving_utils/__init__.py
serving_utils/client.py
serving_utils/freeze_graph.py
serving_utils/loader.py
serving_utils/round_robin_map.py
serving_utils/saver.py
serving_utils/protos/__init__.py
serving_utils/protos/list_models_grpc.py
serving_utils/protos/list_models_pb2.py
serving_utils/protos/list_models_pb2_grpc.py
serving_utils/protos/model_grpc.py
serving_utils/protos/model_pb2.py
serving_utils/protos/model_pb2_grpc.py
serving_utils/protos/predict_grpc.py
serving_utils/protos/predict_pb2.py
serving_utils/protos/predict_pb2_grpc.py
serving_utils/protos/prediction_service_grpc.py
serving_utils/protos/prediction_service_pb2.py
serving_utils/protos/prediction_service_pb2_grpc.py
serving_utils/protos/resource_handle_grpc.py
serving_utils/protos/resource_handle_pb2.py
serving_utils/protos/resource_handle_pb2_grpc.py
serving_utils/protos/tensor_grpc.py
serving_utils/protos/tensor_pb2.py
serving_utils/protos/tensor_pb2_grpc.py
serving_utils/protos/tensor_shape_grpc.py
serving_utils/protos/tensor_shape_pb2.py
serving_utils/protos/tensor_shape_pb2_grpc.py
serving_utils/protos/types_grpc.py
serving_utils/protos/types_pb2.py
serving_utils/protos/types_pb2_grpc.py
serving_utils-0.10.0.dist-info/LICENSE
serving_utils-0.10.0.dist-info/METADATA
serving_utils-0.10.0.dist-info/WHEEL
serving_utils-0.10.0.dist-info/top_level.txt
serving_utils-0.10.0.dist-info/RECORD
