Metadata-Version: 2.1
Name: serving-utils
Version: 0.10.0
Summary: Some utilities for tensorflow serving
Home-page: https://github.com/Yoctol/serving-utils
Author: Po-Hsien Chu
Author-email: cph@yoctol.com
License: MIT
Platform: UNKNOWN
Requires-Python: >=3.6
Requires-Dist: grpclib
Requires-Dist: grpcio-tools
Requires-Dist: numpy (>=1.14.0)
